apiview/__init__.py
apiview/admin.py
apiview/admintools.py
apiview/apps.py
apiview/cache.py
apiview/code.py
apiview/common_view.py
apiview/consumers.py
apiview/des.py
apiview/descriptors.py
apiview/err_code.py
apiview/exceptions.py
apiview/filters.py
apiview/logger.py
apiview/mailtools.py
apiview/middlewares.py
apiview/model.py
apiview/renderers.py
apiview/serializer.py
apiview/utility.py
apiview/validators.py
apiview/view.py
apiview/widgets.py
apiview/management/__init__.py
apiview/management/commands/__init__.py
apiview/management/commands/sync_permissions.py
apiview/static/apiview/css/filter.css
apiview/static/apiview/js/apiview.js
apiview/static/apiview/js/filter.js
apiview/templates/apiview/api.html
apiview/templates/apiview/date_filter.html
apiview/templates/apiview/range_filter.html
apiview/templates/apiview/related_autocomplete.html
apiview/templates/apiview/scripts.html
apiview/templates/apiview/search.html
apiview/templatetags/__init__.py
apiview/templatetags/apiview_tags.py
apiview/views/__init__.py
apiview/views/admin.py
apiview/views/base.py
apiview/views/decorators.py
apiview/views/fields.py
apiview/views/models.py
apiview/views/param.py
apiview/views/rest_framework.py
apiview/views/sites.py
apiview/views/utils.py
apiview/views/widgets.py
apiview/views/dtd/__init__.py
apiview/views/dtd/exceptions.py
apiview/views/dtd/jsonschema.py
apiview/views/dtd/test_jsonschema.py
django_restframework_apiview-1.4.2.dist-info/LICENSE
django_restframework_apiview-1.4.2.dist-info/METADATA
django_restframework_apiview-1.4.2.dist-info/WHEEL
django_restframework_apiview-1.4.2.dist-info/top_level.txt
django_restframework_apiview-1.4.2.dist-info/RECORD
