Metadata-Version: 2.1
Name: django_restframework_apiview
Version: 1.4.2
Summary: Django REST_framework APIView
Home-page: https://github.com/007gzs/django_restframework_apiview
Author: 007gzs
Author-email: 007gzs@sina.com
License: LGPL v3
Keywords: django rest framework api view
Platform: UNKNOWN
Classifier: Development Status :: 3 - Alpha
Classifier: Intended Audience :: Developers
Classifier: Topic :: Software Development :: Build Tools
Classifier: License :: OSI Approved :: GNU Lesser General Public License v3 (LGPLv3)
Classifier: Programming Language :: Python :: 2
Classifier: Programming Language :: Python :: 2.7
Classifier: Programming Language :: Python :: 3
Classifier: Programming Language :: Python :: 3.3
Classifier: Programming Language :: Python :: 3.4
Classifier: Programming Language :: Python :: 3.5
Classifier: Programming Language :: Python :: 3.6
Provides-Extra: test
Provides-Extra: dev
